nexusync/__init__.py
nexusync/nexusync.py
nexusync/config/__init__.py
nexusync/config/settings.py
nexusync/core/__init__.py
nexusync/core/chat_engine.py
nexusync/core/indexer.py
nexusync/core/indexing_functions.py
nexusync/core/querier.py
nexusync/models/__init__.py
nexusync/models/embedding_models.py
nexusync/models/language_models.py
nexusync/utils/__init__.py
nexusync/utils/file_operations.py
nexusync/utils/logging_config.py
nexusync-0.3.6.dist-info/LICENSE.txt
nexusync-0.3.6.dist-info/METADATA
nexusync-0.3.6.dist-info/WHEEL
nexusync-0.3.6.dist-info/top_level.txt
nexusync-0.3.6.dist-info/RECORD
