Metadata-Version: 2.1
Name: nexusync
Version: 0.3.6
Summary: A powerful document indexing and querying tool built on top of LlamaIndex
Home-page: https://github.com/Zakk-Yang/nexusync.git
Author: Zakk Yang
Author-email: zakkyang@protonmail.com
Classifier: Programming Language :: Python :: 3
Classifier: License :: OSI Approved :: MIT License
Classifier: Operating System :: OS Independent
Requires-Python: >=3.10
License-File: LICENSE.txt
Requires-Dist: llama-index
Requires-Dist: llama-index-llms-ollama
Requires-Dist: llama-index-embeddings-huggingface
Requires-Dist: chromadb
Requires-Dist: llama-index-vector-stores-chroma
Requires-Dist: transformers>=4.45.2
Requires-Dist: python-pptx
Requires-Dist: Pillow
Requires-Dist: docx2txt
Requires-Dist: openpyxl
Requires-Dist: python-dotenv
Requires-Dist: spacy
Requires-Dist: flask
